onshape_to_robot/__init__.py
onshape_to_robot/assembly.py
onshape_to_robot/bullet.py
onshape_to_robot/clear_cache.py
onshape_to_robot/config.py
onshape_to_robot/csg.py
onshape_to_robot/edit_shape.py
onshape_to_robot/export.py
onshape_to_robot/exporter.py
onshape_to_robot/exporter_mujoco.py
onshape_to_robot/exporter_sdf.py
onshape_to_robot/exporter_urdf.py
onshape_to_robot/exporter_utils.py
onshape_to_robot/expression.py
onshape_to_robot/features.py
onshape_to_robot/geometry.py
onshape_to_robot/load_robot.py
onshape_to_robot/message.py
onshape_to_robot/mujoco.py
onshape_to_robot/onshape_to_robot.py
onshape_to_robot/processor.py
onshape_to_robot/processor_ball_to_euler.py
onshape_to_robot/processor_collision_as_visual.py
onshape_to_robot/processor_convex_decomposition.py
onshape_to_robot/processor_dummy_base_link.py
onshape_to_robot/processor_fixed_links.py
onshape_to_robot/processor_merge_parts.py
onshape_to_robot/processor_no_collision_meshes.py
onshape_to_robot/processor_scad.py
onshape_to_robot/processor_simplify_stls.py
onshape_to_robot/processors.py
onshape_to_robot/pure_sketch.py
onshape_to_robot/robot.py
onshape_to_robot/robot_builder.py
onshape_to_robot/robot_description.py
onshape_to_robot/shapes.py
onshape_to_robot/simulation.py
onshape_to_robot/stl_combine.py
onshape_to_robot/test.py
onshape_to_robot/assets/scene.xml
onshape_to_robot/bullet/plane.obj
onshape_to_robot/bullet/plane.urdf
onshape_to_robot/onshape_api/__init__.py
onshape_to_robot/onshape_api/cache.py
onshape_to_robot/onshape_api/client.py
onshape_to_robot/onshape_api/onshape.py
onshape_to_robot/onshape_api/utils.py
onshape_to_robot-1.6.9.dist-info/LICENSE
onshape_to_robot-1.6.9.dist-info/METADATA
onshape_to_robot-1.6.9.dist-info/WHEEL
onshape_to_robot-1.6.9.dist-info/entry_points.txt
onshape_to_robot-1.6.9.dist-info/top_level.txt
onshape_to_robot-1.6.9.dist-info/RECORD
