Metadata-Version: 2.1
Name: onshape-to-robot
Version: 1.6.9
Summary: Converting Onshape assembly to robot definition (URDF, SDF, MuJoCo) through Onshape API 
Home-page: https://github.com/rhoban/onshape-to-robot/
Author: Rhoban team
Author-email: team@rhoban.com
License: UNKNOWN
Keywords: robot robotics cad design onshape bullet pybullet mujoco urdf sdf gazebo ros model kinematics
Platform: UNKNOWN
Classifier: Programming Language :: Python :: 3
Classifier: License :: OSI Approved :: MIT License
Classifier: Operating System :: OS Independent
Requires-Python: >=3.9
License-File: LICENSE
Requires-Dist: colorama >=0.4.6
Requires-Dist: commentjson
Requires-Dist: numpy
Requires-Dist: numpy-stl
Requires-Dist: python-dotenv
Requires-Dist: requests
Requires-Dist: transforms3d
